{"api_index.md":"f02bd8a6","api_intl-number-input.currencydisplay.md":"21f35798","api_intl-number-input.numberformatstyle.md":"8aae6058","api_intl-number-input.numberinput._constructor_.md":"1bbc771f","api_intl-number-input.numberinput.decrement.md":"07c21515","api_intl-number-input.numberinput.destroy.md":"82480eba","api_intl-number-input.numberinput.getvalue.md":"68fc2ee0","api_intl-number-input.numberinput.increment.md":"2606c352","api_intl-number-input.numberinput.md":"9a90bde9","api_intl-number-input.numberinput.setoptions.md":"f5ea564f","api_intl-number-input.numberinput.setvalue.md":"68f23f5b","api_intl-number-input.numberinputconstructorargs.el.md":"e372caad","api_intl-number-input.numberinputconstructorargs.md":"f7495ccb","api_intl-number-input.numberinputconstructorargs.onchange.md":"66c2dca8","api_intl-number-input.numberinputconstructorargs.oninput.md":"fd001095","api_intl-number-input.numberinputconstructorargs.options.md":"22e2c92d","api_intl-number-input.numberinputoptions.autodecimaldigits.md":"eeca96fe","api_intl-number-input.numberinputoptions.autosign.md":"d2a8e677","api_intl-number-input.numberinputoptions.currency.md":"5a4218bc","api_intl-number-input.numberinputoptions.currencydisplay.md":"5f5658b6","api_intl-number-input.numberinputoptions.exportvalueasinteger.md":"c3989481","api_intl-number-input.numberinputoptions.formatstyle.md":"d1f585db","api_intl-number-input.numberinputoptions.hidegroupingseparatoronfocus.md":"dc99bff5","api_intl-number-input.numberinputoptions.hidenegligibledecimaldigitsonfocus.md":"2c7b1aca","api_intl-number-input.numberinputoptions.hideprefixorsuffixonfocus.md":"dadbd8d0","api_intl-number-input.numberinputoptions.locale.md":"eb122cad","api_intl-number-input.numberinputoptions.md":"6286ee74","api_intl-number-input.numberinputoptions.precision.md":"7f6c2a15","api_intl-number-input.numberinputoptions.step.md":"a916dff0","api_intl-number-input.numberinputoptions.unit.md":"ba6c440c","api_intl-number-input.numberinputoptions.unitdisplay.md":"80a88683","api_intl-number-input.numberinputoptions.usegrouping.md":"1198b919","api_intl-number-input.numberinputoptions.valuerange.md":"ad231108","api_intl-number-input.numberinputvalue.formatted.md":"4ffc82bb","api_intl-number-input.numberinputvalue.md":"ada88888","api_intl-number-input.numberinputvalue.number.md":"e9dde946","api_intl-number-input.numberrange.max.md":"36e06d56","api_intl-number-input.numberrange.md":"71e9f6f6","api_intl-number-input.numberrange.min.md":"ddf5bd81","api_intl-number-input.unitdisplay.md":"a259982c","guide_index.md":"77b0fbbc","index.md":"479dde59","playground_index.md":"02d752fd"}
